tutor_contrib_pod_autoscaling-20.0.0.dist-info/licenses/LICENSE
tutorpod_autoscaling/__about__.py
tutorpod_autoscaling/__init__.py
tutorpod_autoscaling/hooks.py
tutorpod_autoscaling/plugin.py
tutorpod_autoscaling/patches/.gitignore
tutorpod_autoscaling/patches/k8s-override
tutorpod_autoscaling/patches/kustomization-resources
tutorpod_autoscaling/templates/pod-autoscaling/apps/.gitignore
tutorpod_autoscaling/templates/pod-autoscaling/build/.gitignore
tutorpod_autoscaling/templates/pod-autoscaling/k8s/hpa.yml
tutorpod_autoscaling/templates/pod-autoscaling/k8s/vpa.yml
tutor_contrib_pod_autoscaling-20.0.0.dist-info/METADATA
tutor_contrib_pod_autoscaling-20.0.0.dist-info/WHEEL
tutor_contrib_pod_autoscaling-20.0.0.dist-info/entry_points.txt
tutor_contrib_pod_autoscaling-20.0.0.dist-info/top_level.txt
tutor_contrib_pod_autoscaling-20.0.0.dist-info/RECORD
